Metadata-Version: 1.2
Name: clickpanda
Version: 0.1
Summary: Pandas interface for Clickhouse HTTP API
Home-page: http://github.com/kszucs/pandahouse
Maintainer: Dikiy Pes
Maintainer-email: dikiy.pes@gmail.com
License: BSD
Platform: UNKNOWN
